{"id": "os.path", "path": "c:\\Users\\jeffe\\git\\Pizzaria\\venv\\lib\\site-packages\\mypy\\typeshed\\stdlib\\3\\os\\path.pyi", "mtime": 1589551944, "size": 6160, "hash": "acdaa3ea87796b0c02fe965f95e4be1052fc078d9d6d4ef2a37cc90c0b9a6dc8", "data_mtime": 1589552378, "dependencies": ["os", "sys", "typing", "builtins", "abc"], "suppressed": [], "options": {"implicit_reexport": true, "allow_untyped_globals": false, "always_false": [], "ignore_missing_imports": true, "bazel": false, "allow_redefinition": false, "show_none_errors": true, "mypyc": false, "platform": "win32", "disallow_any_expr": false, "always_true": [], "strict_optional_whitelist": null, "strict_optional": true, "disallow_any_explicit": false, "local_partial_types": false, "warn_unreachable": false, "disallow_any_decorated": false, "follow_imports": "silent", "disallow_untyped_decorators": false, "ignore_errors": false, "warn_return_any": false, "plugins": [], "disallow_untyped_calls": false, "no_implicit_optional": false, "check_untyped_defs": false, "disallow_subclassing_any": false, "warn_no_return": true, "disallow_any_unimported": false, "disallow_untyped_defs": false, "strict_equality": false, "disallow_any_generics": false, "follow_imports_for_stubs": false, "warn_unused_ignores": false, "disallow_incomplete_defs": false}, "dep_prios": [10, 10, 5, 5, 30], "dep_lines": [5, 6, 7, 12, 1], "interface_hash": "56c9467cda14b6b2042926cf9da1e66f299b7db116f269fa9e79840cfb9edd2b", "version_id": "0.770", "ignore_all": true, "plugin_data": null}